{
  "peers": [
    {
      "discovery_host": "182d486531144a6989f14901942c86a0-vp0.us.blockchain.ibm.com",
      "discovery_port": 30002,
      "api_host": "182d486531144a6989f14901942c86a0-vp0.us.blockchain.ibm.com",
      "api_port_tls": 5002,
      "api_port": 5002,
      "event_host": "182d486531144a6989f14901942c86a0-vp0.us.blockchain.ibm.com",
      "event_port": 31002,
      "type": "peer",
      "network_id": "182d486531144a6989f14901942c86a0",
      "container_id": "2997ad6e397b5835754725b4afc4784c1d1bde290b16420b2d725a428559691f",
      "id": "182d486531144a6989f14901942c86a0-vp0",
      "api_url": "https://182d486531144a6989f14901942c86a0-vp0.us.blockchain.ibm.com:5002"
    },
    {
      "discovery_host": "182d486531144a6989f14901942c86a0-vp1.us.blockchain.ibm.com",
      "discovery_port": 30002,
      "api_host": "182d486531144a6989f14901942c86a0-vp1.us.blockchain.ibm.com",
      "api_port_tls": 5002,
      "api_port": 5002,
      "event_host": "182d486531144a6989f14901942c86a0-vp1.us.blockchain.ibm.com",
      "event_port": 31002,
      "type": "peer",
      "network_id": "182d486531144a6989f14901942c86a0",
      "container_id": "b24439322ded085b8707d94c257be913952853a17a75b65826d846a57750000c",
      "id": "182d486531144a6989f14901942c86a0-vp1",
      "api_url": "https://182d486531144a6989f14901942c86a0-vp1.us.blockchain.ibm.com:5002"
    },
    {
      "discovery_host": "182d486531144a6989f14901942c86a0-vp2.us.blockchain.ibm.com",
      "discovery_port": 30002,
      "api_host": "182d486531144a6989f14901942c86a0-vp2.us.blockchain.ibm.com",
      "api_port_tls": 5002,
      "api_port": 5002,
      "event_host": "182d486531144a6989f14901942c86a0-vp2.us.blockchain.ibm.com",
      "event_port": 31002,
      "type": "peer",
      "network_id": "182d486531144a6989f14901942c86a0",
      "container_id": "c00cb2a5bdbd4c51a5a48d9a96a4e40be62972a52b4c0e1f7c2b01d583219a67",
      "id": "182d486531144a6989f14901942c86a0-vp2",
      "api_url": "https://182d486531144a6989f14901942c86a0-vp2.us.blockchain.ibm.com:5002"
    },
    {
      "discovery_host": "182d486531144a6989f14901942c86a0-vp3.us.blockchain.ibm.com",
      "discovery_port": 30002,
      "api_host": "182d486531144a6989f14901942c86a0-vp3.us.blockchain.ibm.com",
      "api_port_tls": 5002,
      "api_port": 5002,
      "event_host": "182d486531144a6989f14901942c86a0-vp3.us.blockchain.ibm.com",
      "event_port": 31002,
      "type": "peer",
      "network_id": "182d486531144a6989f14901942c86a0",
      "container_id": "b90e0e6c7b0194531f4d57a11543f53765c1f9e5d1d04c594a8dfc3be315b761",
      "id": "182d486531144a6989f14901942c86a0-vp3",
      "api_url": "https://182d486531144a6989f14901942c86a0-vp3.us.blockchain.ibm.com:5002"
    }
  ],
  "ca": {
    "182d486531144a6989f14901942c86a0-ca": {
      "url": "182d486531144a6989f14901942c86a0-ca.us.blockchain.ibm.com:30002",
      "discovery_host": "182d486531144a6989f14901942c86a0-ca.us.blockchain.ibm.com",
      "discovery_port": 30002,
      "api_host": "182d486531144a6989f14901942c86a0-ca.us.blockchain.ibm.com",
      "api_port_tls": 30002,
      "api_port": 30002,
      "type": "ca",
      "network_id": "182d486531144a6989f14901942c86a0",
      "container_id": "55c2fef8032d7864619b066207bee1319c6390bca5beed6049d97912503beb0c"
    }
  },
  "users": [
    {
      "enrollId": "admin",
      "enrollSecret": "bff37106a8",
      "affiliation": "group1",
      "username": "admin",
      "secret": "bff37106a8"
    },
    {
      "enrollId": "WebAppAdmin",
      "enrollSecret": "42ccef1163",
      "affiliation": "group1",
      "username": "WebAppAdmin",
      "secret": "42ccef1163"
    },
    {
      "enrollId": "user_type1_0",
      "enrollSecret": "f3f189fbaf",
      "affiliation": "group1",
      "username": "user_type1_0",
      "secret": "f3f189fbaf"
    },
    {
      "enrollId": "user_type1_1",
      "enrollSecret": "59d5db632d",
      "affiliation": "group1",
      "username": "user_type1_1",
      "secret": "59d5db632d"
    },
    {
      "enrollId": "user_type1_2",
      "enrollSecret": "c8ebb8b82e",
      "affiliation": "group1",
      "username": "user_type1_2",
      "secret": "c8ebb8b82e"
    },
    {
      "enrollId": "user_type1_3",
      "enrollSecret": "e4120d2de4",
      "affiliation": "group1",
      "username": "user_type1_3",
      "secret": "e4120d2de4"
    },
    {
      "enrollId": "user_type1_4",
      "enrollSecret": "d6a7c41f31",
      "affiliation": "group1",
      "username": "user_type1_4",
      "secret": "d6a7c41f31"
    },
    {
      "enrollId": "user_type2_0",
      "enrollSecret": "f963394a74",
      "affiliation": "group1",
      "username": "user_type2_0",
      "secret": "f963394a74"
    },
    {
      "enrollId": "user_type2_1",
      "enrollSecret": "c2396c0b50",
      "affiliation": "group1",
      "username": "user_type2_1",
      "secret": "c2396c0b50"
    },
    {
      "enrollId": "user_type2_2",
      "enrollSecret": "c81f5c784c",
      "affiliation": "group1",
      "username": "user_type2_2",
      "secret": "c81f5c784c"
    },
    {
      "enrollId": "user_type2_3",
      "enrollSecret": "3af3d827cd",
      "affiliation": "group1",
      "username": "user_type2_3",
      "secret": "3af3d827cd"
    },
    {
      "enrollId": "user_type2_4",
      "enrollSecret": "7fc4d91aff",
      "affiliation": "group1",
      "username": "user_type2_4",
      "secret": "7fc4d91aff"
    },
    {
      "enrollId": "user_type4_0",
      "enrollSecret": "b03917c7a0",
      "affiliation": "group1",
      "username": "user_type4_0",
      "secret": "b03917c7a0"
    },
    {
      "enrollId": "user_type4_1",
      "enrollSecret": "0fbaa464f4",
      "affiliation": "group1",
      "username": "user_type4_1",
      "secret": "0fbaa464f4"
    },
    {
      "enrollId": "user_type4_2",
      "enrollSecret": "5482726625",
      "affiliation": "group1",
      "username": "user_type4_2",
      "secret": "5482726625"
    },
    {
      "enrollId": "user_type4_3",
      "enrollSecret": "a661a557b1",
      "affiliation": "group1",
      "username": "user_type4_3",
      "secret": "a661a557b1"
    },
    {
      "enrollId": "user_type4_4",
      "enrollSecret": "dec30173fa",
      "affiliation": "group1",
      "username": "user_type4_4",
      "secret": "dec30173fa"
    },
    {
      "enrollId": "user_type8_0",
      "enrollSecret": "0fd4cbeaaf",
      "affiliation": "group1",
      "username": "user_type8_0",
      "secret": "0fd4cbeaaf"
    },
    {
      "enrollId": "user_type8_1",
      "enrollSecret": "c51438b142",
      "affiliation": "group1",
      "username": "user_type8_1",
      "secret": "c51438b142"
    },
    {
      "enrollId": "user_type8_2",
      "enrollSecret": "55ab8324c3",
      "affiliation": "group1",
      "username": "user_type8_2",
      "secret": "55ab8324c3"
    },
    {
      "enrollId": "user_type8_3",
      "enrollSecret": "5445d61e4b",
      "affiliation": "group1",
      "username": "user_type8_3",
      "secret": "5445d61e4b"
    },
    {
      "enrollId": "user_type8_4",
      "enrollSecret": "855f5a1077",
      "affiliation": "group1",
      "username": "user_type8_4",
      "secret": "855f5a1077"
    }
  ],
  "cert": "https://blockchain-certs.mybluemix.net/us.blockchain.ibm.com.cert",
  "cert_path": "/certs/peer/cert.pem"
}